polidoro_model/__init__.py
polidoro_model/base.py
polidoro_model/commands.py
polidoro_model-0.1.0.dist-info/LICENSE
polidoro_model-0.1.0.dist-info/METADATA
polidoro_model-0.1.0.dist-info/WHEEL
polidoro_model-0.1.0.dist-info/top_level.txt
polidoro_model-0.1.0.dist-info/RECORD
