Metadata-Version: 2.1
Name: polidoro-model
Version: 0.1.0
Summary: Polidoro Model.
Home-page: https://github.com/heitorpolidoro/polidoro-model
Author: Heitor Polidoro
License: unlicense
Platform: UNKNOWN
Classifier: Programming Language :: Python :: 3
Classifier: License :: OSI Approved :: MIT License
Classifier: Operating System :: OS Independent
License-File: LICENSE
Requires-Dist: SQLAlchemy
